neuroembed/__init__.py
neuroembed/context.py
neuroembed/core.py
neuroembed/explainability.py
neuroembed/strategies.py
neuroembed/encoders/__init__.py
neuroembed/encoders/base.py
neuroembed/encoders/fasttext_encoder.py
neuroembed/encoders/sentence_transformer.py
neuroembed/integrations/__init__.py
neuroembed/integrations/langchain.py
neuroembed/integrations/llamaindex.py
neuroembed/integrations/vectordb.py
neuroembed-0.2.0.dist-info/licenses/License
neuroembed-0.2.0.dist-info/METADATA
neuroembed-0.2.0.dist-info/WHEEL
neuroembed-0.2.0.dist-info/top_level.txt
neuroembed-0.2.0.dist-info/RECORD
