Metadata-Version: 2.4
Name: neuroembed
Version: 0.2.0
Summary: Model-agnostic semantic embedding enrichment framework with context-aware blending strategies
Author-email: Umeshkumar Pal <umeshkumar667@gmail.com>
License: MIT
Project-URL: Homepage, https://github.com/Umeshkumar667/NeuroEmbed
Project-URL: Documentation, https://github.com/Umeshkumar667/NeuroEmbed#readme
Project-URL: Repository, https://github.com/Umeshkumar667/NeuroEmbed.git
Project-URL: Issues, https://github.com/Umeshkumar667/NeuroEmbed/issues
Project-URL: Changelog, https://github.com/Umeshkumar667/NeuroEmbed/blob/main/CHANGELOG.md
Keywords: embeddings,semantic-search,rag,retrieval-augmented-generation,nlp,machine-learning,context-aware,vector-search,langchain,llamaindex
Classifier: Development Status :: 4 - Beta
Classifier: Intended Audience :: Developers
Classifier: Intended Audience :: Science/Research
Classifier: License :: OSI Approved :: MIT License
Classifier: Operating System :: OS Independent
Classifier: Programming Language :: Python :: 3
Classifier: Programming Language :: Python :: 3.9
Classifier: Programming Language :: Python :: 3.10
Classifier: Programming Language :: Python :: 3.11
Classifier: Programming Language :: Python :: 3.12
Classifier: Topic :: Scientific/Engineering :: Artificial Intelligence
Classifier: Topic :: Text Processing :: Linguistic
Requires-Python: >=3.9
License-File: License
Requires-Dist: numpy>=1.21.0
Requires-Dist: sentence-transformers>=2.2.0
Provides-Extra: langchain
Requires-Dist: langchain-core>=0.1.0; extra == "langchain"
Provides-Extra: llamaindex
Requires-Dist: llama-index-core>=0.10.0; extra == "llamaindex"
Provides-Extra: vectordb
Requires-Dist: chromadb>=0.4.0; extra == "vectordb"
Provides-Extra: viz
Requires-Dist: matplotlib>=3.5.0; extra == "viz"
Provides-Extra: all
Requires-Dist: langchain-core>=0.1.0; extra == "all"
Requires-Dist: llama-index-core>=0.10.0; extra == "all"
Requires-Dist: chromadb>=0.4.0; extra == "all"
Requires-Dist: matplotlib>=3.5.0; extra == "all"
Provides-Extra: dev
Requires-Dist: pytest>=7.0.0; extra == "dev"
Requires-Dist: pytest-cov>=4.0.0; extra == "dev"
Requires-Dist: black>=23.0.0; extra == "dev"
Requires-Dist: isort>=5.12.0; extra == "dev"
Requires-Dist: mypy>=1.0.0; extra == "dev"
Dynamic: license-file
